winfetch/__init__.py
winfetch/__main__.py
windowsfetch-1.0.2.dist-info/LICENSE
windowsfetch-1.0.2.dist-info/METADATA
windowsfetch-1.0.2.dist-info/WHEEL
windowsfetch-1.0.2.dist-info/entry_points.txt
windowsfetch-1.0.2.dist-info/top_level.txt
windowsfetch-1.0.2.dist-info/RECORD
