Metadata-Version: 2.1
Name: windowsfetch
Version: 1.0.2
Summary: command: winfetch. i made this as a funny windows version of neofetch in like an hour. 
Home-page: UNKNOWN
Author: gamerjamer43
Author-email: gamerjamer43@protonmail.com
License: GNU GENERAL PUBLIC LICENSE V3
Platform: windows
